django_slack/__init__.py
django_slack/api.py
django_slack/app_settings.py
django_slack/backends.py
django_slack/exceptions.py
django_slack/log.py
django_slack/models.py
django_slack/tasks.py
django_slack/utils.py
django_slack/templates/django_slack/channel
django_slack/templates/django_slack/endpoint_url
django_slack/templates/django_slack/exception.slack
django_slack/templates/django_slack/icon_emoji
django_slack/templates/django_slack/icon_url
django_slack/templates/django_slack/text
django_slack/templates/django_slack/token
django_slack/templates/django_slack/username
django_slack/templatetags/__init__.py
django_slack/templatetags/django_slack.py
tests/__init__.py
tests/backends.py
tests/settings.py
tests/test_escaping.py
tests/test_override.py
tests/test_validation.py
django_slack-5.19.0.dist-info/COPYING
django_slack-5.19.0.dist-info/METADATA
django_slack-5.19.0.dist-info/WHEEL
django_slack-5.19.0.dist-info/top_level.txt
django_slack-5.19.0.dist-info/RECORD
