Metadata-Version: 2.1
Name: django-slack
Version: 5.19.0
Summary: Provides easy-to-use integration between Django projects and the Slack group chat and IM tool.
Home-page: https://chris-lamb.co.uk/projects/django-slack
Author: Chris Lamb
Author-email: chris@chris-lamb.co.uk
License: BSD-3-Clause
Requires-Python: >=3.6
License-File: COPYING
Requires-Dist: Django (>=3.2)
Requires-Dist: requests
